Ramin123455/__init__.py
Ramin123455/diff_exp.py
Ramin123455/dist.py
Ramin123455/filter_genes.py
Ramin123455/hyper.py
Ramin123455/mca.py
Ramin123455/mca_steps.py
Ramin123455/preprocessData.py
Ramin123455/visual.py
ramin123455-1.0.0.dist-info/METADATA
ramin123455-1.0.0.dist-info/WHEEL
ramin123455-1.0.0.dist-info/licenses/LICENSE.txt
ramin123455-1.0.0.dist-info/RECORD
