Metadata-Version: 2.3
Name: Ramin123455
Version: 1.0.0
Summary: Python package for cell identity recognition at individual cell level from single-cell RNA-seq data. Cell types for unknown cells are predicted, through a statistical approach, using raw gene expresssion data among a list of cells, and a gene marker dataset consisting of a list of genes found in known cell types/gene sets.
Project-URL: Homepage, https://github.com/RockLee117/sc-pred
Project-URL: Issues, https://github.com/RockLee117/sc-pred/issues
Author-email: Ramin Mohammadi <rammoh5346@gmail.com>
License-File: LICENSE.txt
Classifier: License :: OSI Approved :: GNU General Public License v3 (GPLv3)
Classifier: Operating System :: OS Independent
Classifier: Programming Language :: Python :: 3
Requires-Python: >=3.11
Requires-Dist: anndata>=0.9.1
Requires-Dist: numpy>=1.24.4
Requires-Dist: pandas>=2.1.4
Requires-Dist: plotly>=5.16.1
Requires-Dist: scanpy>=1.9.3
Requires-Dist: scikit-learn>=1.3.0
Requires-Dist: scipy>=1.11.1
Requires-Dist: umap-learn>=0.5.3
